phrase_api/__init__.py
phrase_api/api_client.py
phrase_api/api_response.py
phrase_api/configuration.py
phrase_api/exceptions.py
phrase_api/py.typed
phrase_api/rest.py
phrase_api/api/__init__.py
phrase_api/api/accounts_api.py
phrase_api/api/authorizations_api.py
phrase_api/api/automations_api.py
phrase_api/api/blacklisted_keys_api.py
phrase_api/api/branches_api.py
phrase_api/api/comment_reactions_api.py
phrase_api/api/comment_replies_api.py
phrase_api/api/comments_api.py
phrase_api/api/custom_metadata_api.py
phrase_api/api/distributions_api.py
phrase_api/api/documents_api.py
phrase_api/api/figma_attachments_api.py
phrase_api/api/formats_api.py
phrase_api/api/glossaries_api.py
phrase_api/api/glossary_term_translations_api.py
phrase_api/api/glossary_terms_api.py
phrase_api/api/icu_api.py
phrase_api/api/invitations_api.py
phrase_api/api/job_annotations_api.py
phrase_api/api/job_comments_api.py
phrase_api/api/job_locales_api.py
phrase_api/api/job_template_locales_api.py
phrase_api/api/job_templates_api.py
phrase_api/api/jobs_api.py
phrase_api/api/keys_api.py
phrase_api/api/keys_figma_attachments_api.py
phrase_api/api/linked_keys_api.py
phrase_api/api/locale_downloads_api.py
phrase_api/api/locales_api.py
phrase_api/api/members_api.py
phrase_api/api/notification_groups_api.py
phrase_api/api/notifications_api.py
phrase_api/api/orders_api.py
phrase_api/api/organization_job_template_locales_api.py
phrase_api/api/organization_job_templates_api.py
phrase_api/api/projects_api.py
phrase_api/api/quality_performance_score_api.py
phrase_api/api/release_triggers_api.py
phrase_api/api/releases_api.py
phrase_api/api/repo_sync_events_api.py
phrase_api/api/repo_syncs_api.py
phrase_api/api/reports_api.py
phrase_api/api/screenshot_markers_api.py
phrase_api/api/screenshots_api.py
phrase_api/api/search_api.py
phrase_api/api/spaces_api.py
phrase_api/api/style_guides_api.py
phrase_api/api/tags_api.py
phrase_api/api/teams_api.py
phrase_api/api/translations_api.py
phrase_api/api/uploads_api.py
phrase_api-3.15.0.dist-info/METADATA
phrase_api-3.15.0.dist-info/WHEEL
phrase_api-3.15.0.dist-info/top_level.txt
phrase_api-3.15.0.dist-info/RECORD
